maniV2/__init__.py
maniV2/job.py
maniV2/run_at.py
maniV2/scheduler.py
maniV2/util.py
maniV2-1.0.0.dist-info/METADATA
maniV2-1.0.0.dist-info/WHEEL
maniV2-1.0.0.dist-info/top_level.txt
maniV2-1.0.0.dist-info/RECORD
