Metadata-Version: 2.1
Name: maniV2
Version: 1.0.0
Summary: Distributed cron
Home-page: https://git.target.com/aishwat/mani.git
Author: Aishwat
Author-email: aishwat.singh@target.com
License: UNKNOWN
Keywords: cron,distributed,redis
Platform: UNKNOWN
Classifier: Environment :: Console
Classifier: Intended Audience :: Developers
Classifier: Operating System :: Unix
Classifier: Operating System :: POSIX
Classifier: Programming Language :: Python
Classifier: Topic :: System
Classifier: Topic :: Software Development
Classifier: Development Status :: 4 - Beta
Requires-Dist: redis
Requires-Dist: python-redis-lock
Requires-Dist: pytz
